SCRIP/Constants.py
SCRIP/__init__.py
SCRIP/start.py
SCRIP/conf/GRCh38_refgenes.txt
SCRIP/conf/GRCm38_refgenes.txt
SCRIP/conf/__init__.py
SCRIP/conf/config.py
SCRIP/conf/config.yml
SCRIP/enhancement/__init__.py
SCRIP/enhancement/enhance.py
SCRIP/enrichment/__init__.py
SCRIP/enrichment/bed_generation.py
SCRIP/enrichment/calculation.py
SCRIP/enrichment/enrich.py
SCRIP/enrichment/post_processing.py
SCRIP/enrichment/search.py
SCRIP/enrichment/utils.py
SCRIP/enrichment/validation.py
SCRIP/imputation/__init__.py
SCRIP/imputation/impute.py
SCRIP/index/index.py
SCRIP/targets/__init__.py
SCRIP/targets/target.py
SCRIP/utilities/__init__.py
SCRIP/utilities/convert_format.py
SCRIP/utilities/convert_seurat2anndata.py
SCRIP/utilities/utils.py
SCRIP-0.1.240603.dist-info/LICENSE
SCRIP-0.1.240603.dist-info/METADATA
SCRIP-0.1.240603.dist-info/WHEEL
SCRIP-0.1.240603.dist-info/entry_points.txt
SCRIP-0.1.240603.dist-info/top_level.txt
SCRIP-0.1.240603.dist-info/RECORD
