Metadata-Version: 2.1
Name: SCRIP
Version: 0.1.240603
Summary: A package for single cell ATAC-seq analysis
Author: Xin Dong
Author-email: xindong9511@gmail.com
Requires-Python: >=3.8.12, !=3.9
License-File: LICENSE
Requires-Dist: numba >=0.51.2
Requires-Dist: numpy >=1.18
Requires-Dist: pandas >=1.3.3
Requires-Dist: cython >=0.29.22
Requires-Dist: ruamel.yaml
Requires-Dist: anndata >=0.7.6
Requires-Dist: anndata2ri >=1.0.6
Requires-Dist: pyranges >=0.0.95
Requires-Dist: pybedtools >=0.8.2
Requires-Dist: matplotlib >=3.1.2
Requires-Dist: scikit-learn
Requires-Dist: scipy
Requires-Dist: scanpy >=1.7.1
